dataShepherd.py
dataProcessing/dataProcessing.py
dataShepherd-0.0.9.dist-info/METADATA
dataShepherd-0.0.9.dist-info/WHEEL
dataShepherd-0.0.9.dist-info/top_level.txt
dataShepherd-0.0.9.dist-info/RECORD
